pasl/__init__.py
pasl/execsteps.py
pasl/shell/__init__.py
pasl/shell/exec_module.py
pasl/shell/rm_module.py
pasl/shell/search_module.py
pypasl-0.1.2.dist-info/METADATA
pypasl-0.1.2.dist-info/WHEEL
pypasl-0.1.2.dist-info/top_level.txt
pypasl-0.1.2.dist-info/RECORD
